[
    {
        "name": "Member Last Name",
        "type": "text box",
        "coordinates": {
            "x": 100,
            "y": 150
        },
        "dimensions": {
            "width": 200,
            "height": 20
        },
        "page": 1,
        "value": "Chen"
    },
    {
        "name": "Member First Name",
        "type": "text box",
        "coordinates": {
            "x": 100,
            "y": 180
        },
        "dimensions": {
            "width": 200,
            "height": 20
        },
        "page": 1,
        "value": "Amy"
    },
    {
        "name": "Medicaid ID Number",
        "type": "text box",
        "coordinates": {
            "x": 100,
            "y": 210
        },
        "dimensions": {
            "width": 200,
            "height": 20
        },
        "page": 1,
        "value": ""
    },
    {
        "name": "Date of Birth",
        "type": "text box",
        "coordinates": {
            "x": 100,
            "y": 240
        },
        "dimensions": {
            "width": 200,
            "height": 20
        },
        "page": 1,
        "value": "05/23/1983"
    },
    {
        "name": "Weight in Kilograms",
        "type": "text box",
        "coordinates": {
            "x": 100,
            "y": 270
        },
        "dimensions": {
            "width": 200,
            "height": 20
        },
        "page": 1,
        "value": "50.9"
    },
    {
        "name": "Prescriber Last Name",
        "type": "text box",
        "coordinates": {
            "x": 100,
            "y": 320
        },
        "dimensions": {
            "width": 200,
            "height": 20
        },
        "page": 1,
        "value": "Nicole"
    },
    {
        "name": "Prescriber First Name",
        "type": "text box",
        "coordinates": {
            "x": 100,
            "y": 350
        },
        "dimensions": {
            "width": 200,
            "height": 20
        },
        "page": 1,
        "value": "Angela"
    },
    {
        "name": "NPI Number",
        "type": "text box",
        "coordinates": {
            "x": 100,
            "y": 380
        },
        "dimensions": {
            "width": 200,
            "height": 20
        },
        "page": 1,
        "value": ""
    },
    {
        "name": "Phone Number",
        "type": "text box",
        "coordinates": {
            "x": 100,
            "y": 410
        },
        "dimensions": {
            "width": 200,
            "height": 20
        },
        "page": 1,
        "value": "421-771-9001"
    },
    {
        "name": "Fax Number",
        "type": "text box",
        "coordinates": {
            "x": 100,
            "y": 440
        },
        "dimensions": {
            "width": 200,
            "height": 20
        },
        "page": 1,
        "value": "421-771-843"
    },
    {
        "name": "Drug Name",
        "type": "text box",
        "coordinates": {
            "x": 100,
            "y": 490
        },
        "dimensions": {
            "width": 200,
            "height": 20
        },
        "page": 1,
        "value": "Botox"
    },
    {
        "name": "Drug Strength",
        "type": "text box",
        "coordinates": {
            "x": 100,
            "y": 520
        },
        "dimensions": {
            "width": 200,
            "height": 20
        },
        "page": 1,
        "value": "190 units"
    },
    {
        "name": "Length of Therapy",
        "type": "text box",
        "coordinates": {
            "x": 100,
            "y": 550
        },
        "dimensions": {
            "width": 200,
            "height": 20
        },
        "page": 1,
        "value": ""
    },
    {
        "name": "Drug Form",
        "type": "text box",
        "coordinates": {
            "x": 100,
            "y": 580
        },
        "dimensions": {
            "width": 200,
            "height": 20
        },
        "page": 1,
        "value": "Injection"
    },
    {
        "name": "Dosing Frequency",
        "type": "text box",
        "coordinates": {
            "x": 100,
            "y": 610
        },
        "dimensions": {
            "width": 200,
            "height": 20
        },
        "page": 1,
        "value": "Every 3 months"
    },
    {
        "name": "Quantity",
        "type": "text box",
        "coordinates": {
            "x": 100,
            "y": 640
        },
        "dimensions": {
            "width": 200,
            "height": 20
        },
        "page": 1,
        "value": "190 units"
    },
    {
        "name": "Member's Last Name (Page 2)",
        "type": "text box",
        "coordinates": {
            "x": 100,
            "y": 150
        },
        "dimensions": {
            "width": 200,
            "height": 20
        },
        "page": 2,
        "value": "Chen"
    },
    {
        "name": "Member's First Name (Page 2)",
        "type": "text box",
        "coordinates": {
            "x": 100,
            "y": 180
        },
        "dimensions": {
            "width": 200,
            "height": 20
        },
        "page": 2,
        "value": "Amy"
    },
    {
        "name": "Diagnosis of Migraine",
        "type": "checkbox",
        "coordinates": {
            "x": 250,
            "y": 350
        },
        "dimensions": {
            "width": 20,
            "height": 20
        },
        "page": 2,
        "value": "checked"
    },
    {
        "name": "Age >= 18",
        "type": "checkbox",
        "coordinates": {
            "x": 250,
            "y": 380
        },
        "dimensions": {
            "width": 20,
            "height": 20
        },
        "page": 2,
        "value": "checked"
    },
    {
        "name": "Utilizing Prophylactic Intervention",
        "type": "checkbox",
        "coordinates": {
            "x": 250,
            "y": 410
        },
        "dimensions": {
            "width": 20,
            "height": 20
        },
        "page": 2,
        "value": "checked"
    },
    {
        "name": "Diagnosis of Chronic Migraines",
        "type": "checkbox",
        "coordinates": {
            "x": 250,
            "y": 440
        },
        "dimensions": {
            "width": 20,
            "height": 20
        },
        "page": 2,
        "value": "checked"
    },
    {
        "name": "Address",
        "type": "text box",
        "coordinates": {
            "x": 100,
            "y": 150
        },
        "dimensions": {
            "width": 200,
            "height": 20
        },
        "page": 1,
        "value": "2751 Market DR"
    },
    {
        "name": "City",
        "type": "text box",
        "coordinates": {
            "x": 100,
            "y": 180
        },
        "dimensions": {
            "width": 200,
            "height": 20
        },
        "page": 1,
        "value": "HILLDALE"
    },
    {
        "name": "State",
        "type": "text box",
        "coordinates": {
            "x": 100,
            "y": 210
        },
        "dimensions": {
            "width": 200,
            "height": 20
        },
        "page": 1,
        "value": "TN"
    },
    {
        "name": "Zipcode",
        "type": "text box",
        "coordinates": {
            "x": 100,
            "y": 240
        },
        "dimensions": {
            "width": 200,
            "height": 20
        },
        "page": 1,
        "value": "37253-2973"
    },
    {
        "name": "Home Phone Number",
        "type": "text box",
        "coordinates": {
            "x": 100,
            "y": 270
        },
        "dimensions": {
            "width": 200,
            "height": 20
        },
        "page": 1,
        "value": "615-593-1048"
    },
    {
        "name": "Cell Phone Number",
        "type": "text box",
        "coordinates": {
            "x": 100,
            "y": 300
        },
        "dimensions": {
            "width": 200,
            "height": 20
        },
        "page": 1,
        "value": "615-593-1048"
    },
    {
        "name": "Social Security Number",
        "type": "text box",
        "coordinates": {
            "x": 100,
            "y": 330
        },
        "dimensions": {
            "width": 200,
            "height": 20
        },
        "page": 1,
        "value": "xxx-xx-8110"
    },
    {
        "name": "Insurance",
        "type": "text box",
        "coordinates": {
            "x": 100,
            "y": 360
        },
        "dimensions": {
            "width": 200,
            "height": 20
        },
        "page": 1,
        "value": "ABS OF TN"
    },
    {
        "name": "Religion",
        "type": "text box",
        "coordinates": {
            "x": 100,
            "y": 390
        },
        "dimensions": {
            "width": 200,
            "height": 20
        },
        "page": 1,
        "value": "Unknown"
    },
    {
        "name": "Preferred Language",
        "type": "text box",
        "coordinates": {
            "x": 100,
            "y": 420
        },
        "dimensions": {
            "width": 200,
            "height": 20
        },
        "page": 1,
        "value": "English, Mandarin"
    },
    {
        "name": "Preferred Written Language",
        "type": "text box",
        "coordinates": {
            "x": 100,
            "y": 450
        },
        "dimensions": {
            "width": 200,
            "height": 20
        },
        "page": 1,
        "value": "English, Mandarin"
    },
    {
        "name": "Gender Identity",
        "type": "text box",
        "coordinates": {
            "x": 100,
            "y": 480
        },
        "dimensions": {
            "width": 200,
            "height": 20
        },
        "page": 1,
        "value": "Female"
    },
    {
        "name": "Race",
        "type": "text box",
        "coordinates": {
            "x": 100,
            "y": 510
        },
        "dimensions": {
            "width": 200,
            "height": 20
        },
        "page": 1,
        "value": "Asian"
    },
    {
        "name": "Ethnic Group",
        "type": "text box",
        "coordinates": {
            "x": 100,
            "y": 540
        },
        "dimensions": {
            "width": 200,
            "height": 20
        },
        "page": 1,
        "value": "Not Hispanic, Latino/a, or Spanish origin"
    },
    {
        "name": "Allergies",
        "type": "text box",
        "coordinates": {
            "x": 100,
            "y": 570
        },
        "dimensions": {
            "width": 200,
            "height": 20
        },
        "page": 1,
        "value": "No Known Allergies"
    },
    {
        "name": "Code Status",
        "type": "text box",
        "coordinates": {
            "x": 100,
            "y": 600
        },
        "dimensions": {
            "width": 200,
            "height": 20
        },
        "page": 1,
        "value": "Not on file"
    },
    {
        "name": "Admitting Provider",
        "type": "text box",
        "coordinates": {
            "x": 100,
            "y": 630
        },
        "dimensions": {
            "width": 200,
            "height": 20
        },
        "page": 1,
        "value": ""
    },
    {
        "name": "Admission Date/Time",
        "type": "text box",
        "coordinates": {
            "x": 100,
            "y": 660
        },
        "dimensions": {
            "width": 200,
            "height": 20
        },
        "page": 1,
        "value": ""
    },
    {
        "name": "Expected Length of Stay",
        "type": "text box",
        "coordinates": {
            "x": 100,
            "y": 690
        },
        "dimensions": {
            "width": 200,
            "height": 20
        },
        "page": 1,
        "value": ""
    },
    {
        "name": "Length of Stay",
        "type": "text box",
        "coordinates": {
            "x": 100,
            "y": 720
        },
        "dimensions": {
            "width": 200,
            "height": 20
        },
        "page": 1,
        "value": "0h"
    },
    {
        "name": "Discharge Provider",
        "type": "text box",
        "coordinates": {
            "x": 100,
            "y": 750
        },
        "dimensions": {
            "width": 200,
            "height": 20
        },
        "page": 1,
        "value": ""
    },
    {
        "name": "Discharge Date",
        "type": "text box",
        "coordinates": {
            "x": 100,
            "y": 780
        },
        "dimensions": {
            "width": 200,
            "height": 20
        },
        "page": 1,
        "value": ""
    },
    {
        "name": "Discharge Disposition",
        "type": "text box",
        "coordinates": {
            "x": 100,
            "y": 810
        },
        "dimensions": {
            "width": 200,
            "height": 20
        },
        "page": 1,
        "value": ""
    },
    {
        "name": "Discharge Destination",
        "type": "text box",
        "coordinates": {
            "x": 100,
            "y": 840
        },
        "dimensions": {
            "width": 200,
            "height": 20
        },
        "page": 1,
        "value": ""
    },
    {
        "name": "Attending Provider",
        "type": "text box",
        "coordinates": {
            "x": 100,
            "y": 870
        },
        "dimensions": {
            "width": 200,
            "height": 20
        },
        "page": 1,
        "value": ""
    },
    {
        "name": "Isolation",
        "type": "text box",
        "coordinates": {
            "x": 100,
            "y": 900
        },
        "dimensions": {
            "width": 200,
            "height": 20
        },
        "page": 1,
        "value": "None"
    },
    {
        "name": "Infection",
        "type": "text box",
        "coordinates": {
            "x": 100,
            "y": 930
        },
        "dimensions": {
            "width": 200,
            "height": 20
        },
        "page": 1,
        "value": "None"
    },
    {
        "name": "Height",
        "type": "text box",
        "coordinates": {
            "x": 100,
            "y": 960
        },
        "dimensions": {
            "width": 200,
            "height": 20
        },
        "page": 1,
        "value": ""
    },
    {
        "name": "Admission Comments",
        "type": "text box",
        "coordinates": {
            "x": 100,
            "y": 990
        },
        "dimensions": {
            "width": 200,
            "height": 20
        },
        "page": 1,
        "value": "None"
    },
    {
        "name": "Principal Problem",
        "type": "text box",
        "coordinates": {
            "x": 100,
            "y": 1020
        },
        "dimensions": {
            "width": 200,
            "height": 20
        },
        "page": 1,
        "value": "None"
    },
    {
        "name": "Prescriber Last Name",
        "type": "text box",
        "coordinates": {
            "x": 100,
            "y": 1050
        },
        "dimensions": {
            "width": 200,
            "height": 20
        },
        "page": 1,
        "value": "Nicole"
    },
    {
        "name": "Prescriber First Name",
        "type": "text box",
        "coordinates": {
            "x": 100,
            "y": 1080
        },
        "dimensions": {
            "width": 200,
            "height": 20
        },
        "page": 1,
        "value": "Angela"
    },
    {
        "name": "NPI Number",
        "type": "text box",
        "coordinates": {
            "x": 100,
            "y": 1110
        },
        "dimensions": {
            "width": 200,
            "height": 20
        },
        "page": 1,
        "value": ""
    },
    {
        "name": "Phone Number",
        "type": "text box",
        "coordinates": {
            "x": 100,
            "y": 1140
        },
        "dimensions": {
            "width": 200,
            "height": 20
        },
        "page": 1,
        "value": "421-771-9001"
    },
    {
        "name": "Fax Number",
        "type": "text box",
        "coordinates": {
            "x": 100,
            "y": 1170
        },
        "dimensions": {
            "width": 200,
            "height": 20
        },
        "page": 1,
        "value": "421-771-843"
    },
    {
        "name": "Drug Name",
        "type": "text box",
        "coordinates": {
            "x": 100,
            "y": 1200
        },
        "dimensions": {
            "width": 200,
            "height": 20
        },
        "page": 1,
        "value": "Botox"
    },
    {
        "name": "Drug Strength",
        "type": "text box",
        "coordinates": {
            "x": 100,
            "y": 1230
        },
        "dimensions": {
            "width": 200,
            "height": 20
        },
        "page": 1,
        "value": "190 units"
    },
    {
        "name": "Length of Therapy",
        "type": "text box",
        "coordinates": {
            "x": 100,
            "y": 1260
        },
        "dimensions": {
            "width": 200,
            "height": 20
        },
        "page": 1,
        "value": ""
    },
    {
        "name": "Drug Form",
        "type": "text box",
        "coordinates": {
            "x": 100,
            "y": 1290
        },
        "dimensions": {
            "width": 200,
            "height": 20
        },
        "page": 1,
        "value": "Injection"
    },
    {
        "name": "Dosing Frequency",
        "type": "text box",
        "coordinates": {
            "x": 100,
            "y": 1320
        },
        "dimensions": {
            "width": 200,
            "height": 20
        },
        "page": 1,
        "value": "Every 3 months"
    },
    {
        "name": "Quantity",
        "type": "text box",
        "coordinates": {
            "x": 100,
            "y": 1350
        },
        "dimensions": {
            "width": 200,
            "height": 20
        },
        "page": 1,
        "value": "190 units"
    },
    {
        "name": "Member's Last Name (Page 2)",
        "type": "text box",
        "coordinates": {
            "x": 100,
            "y": 1380
        },
        "dimensions": {
            "width": 200,
            "height": 20
        },
        "page": 2,
        "value": "Chen"
    },
    {
        "name": "Member's First Name (Page 2)",
        "type": "text box",
        "coordinates": {
            "x": 100,
            "y": 1410
        },
        "dimensions": {
            "width": 200,
            "height": 20
        },
        "page": 2,
        "value": "Amy"
    },
    {
        "name": "Diagnosis of Migraine",
        "type": "checkbox",
        "coordinates": {
            "x": 250,
            "y": 1440
        },
        "dimensions": {
            "width": 20,
            "height": 20
        },
        "page": 2,
        "value": "checked"
    },
    {
        "name": "Age >= 18",
        "type": "checkbox",
        "coordinates": {
            "x": 250,
            "y": 1470
        },
        "dimensions": {
            "width": 20,
            "height": 20
        },
        "page": 2,
        "value": "checked"
    },
    {
        "name": "Utilizing Prophylactic Intervention",
        "type": "checkbox",
        "coordinates": {
            "x": 250,
            "y": 1500
        },
        "dimensions": {
            "width": 20,
            "height": 20
        },
        "page": 2,
        "value": "checked"
    },
    {
        "name": "Diagnosis of Chronic Migraines",
        "type": "checkbox",
        "coordinates": {
            "x": 250,
            "y": 1530
        },
        "dimensions": {
            "width": 20,
            "height": 20
        },
        "page": 2,
        "value": "checked"
    }
]